<metadata xml:lang="en"><Esri><CreaDate>20150701</CreaDate><CreaTime>13362800</CreaTime><ArcGISFormat>1.0</ArcGISFormat><SyncOnce>TRUE</SyncOnce><ModDate>20150707</ModDate><ModTime>13215700</ModTime><scaleRange><minScale>150000000</minScale><maxScale>5000</maxScale></scaleRange><ArcGISProfile>ItemDescription</ArcGISProfile></Esri><tool name="bioclim" displayname="Add Bioclim Data" toolboxalias="Tools for groundwater wells" xmlns=""><arcToolboxHelpPath>c:\program files (x86)\arcgis\desktop10.3\Help\gp</arcToolboxHelpPath><parameters><param name="wells" displayname="Input Wells" type="Required" direction="Input" datatype="Feature Layer" expression="wells"/><param name="bioclim" displayname="Bioclim raster" type="Required" direction="Input" datatype="Raster Dataset" expression="bioclim"/><param name="results" displayname="Output location" type="Required" direction="Output" datatype="Table" expression="results"/></parameters><summary>&lt;DIV STYLE="text-align:Left;"&gt;&lt;DIV&gt;&lt;P&gt;&lt;SPAN&gt;Extracts all values for the bands of the WorldClim climate raster to a table for each of the points.&lt;/SPAN&gt;&lt;/P&gt;&lt;/DIV&gt;&lt;/DIV&gt;</summary></tool><dataIdInfo><idCitation><resTitle>Add Bioclim Data</resTitle></idCitation><idAbs>&lt;DIV STYLE="text-align:Left;"&gt;&lt;DIV&gt;&lt;P&gt;&lt;SPAN&gt;Extracts all values for the bands of the WorldClim climate raster to a table for each of the points.&lt;/SPAN&gt;&lt;/P&gt;&lt;/DIV&gt;&lt;/DIV&gt;</idAbs><searchKeys><keyword>climate</keyword><keyword>bioclim</keyword></searchKeys></dataIdInfo><distInfo><distributor><distorFormat><formatName>ArcToolbox Tool</formatName></distorFormat></distributor></distInfo><mdHrLv><ScopeCd value="005"></ScopeCd></mdHrLv></metadata>
